khmercut/__init__.py
khmercut/crf_ner_10000.crfsuite
khmercut-0.0.2.data/scripts/khmercut
khmercut-0.0.2.dist-info/METADATA
khmercut-0.0.2.dist-info/WHEEL
khmercut-0.0.2.dist-info/top_level.txt
khmercut-0.0.2.dist-info/RECORD
