Metadata-Version: 2.1
Name: khmercut
Version: 0.0.2
Summary: A (fast) Khmer word segmentation toolkit.
Home-page: https://github.com/seanghay/khmercut
Author: Seanghay Yath
Author-email: seanghay.dev@gmail.com
License: Apache License 2.0
Classifier: Programming Language :: Python :: 3
Classifier: Operating System :: OS Independent
Classifier: Intended Audience :: Developers
Classifier: Natural Language :: English
Requires-Python: >3.5
Requires-Dist: python-crfsuite (==0.9.9)
Requires-Dist: khmernormalizer (==0.0.4)
Requires-Dist: tqdm (==4.65.0)
Provides-Extra: test
Requires-Dist: pytest ; extra == 'test'
Requires-Dist: coverage ; extra == 'test'
